Workbook

Sheet README
A1: Sheet | B1: How to use
A2: Outreach | B2: Log every prospect. When Stage -> Closed, copy Shop/Slug into Customers + Finance (revenue row). Set Next_FollowUp; overdue dates highlight red.
A3: Merchant_Stats | B3: Every Monday copy per-shop numbers from /dashboard. Total + Conversion% auto-calc. 1 row per merchant per week.
A4: Product_Feedback | B4: Every merchant comment about StarGate itself (bug, UX, feature, pricing, churn risk). Triage weekly: Priority + Status; follow up with the merchant before renewals.
A5: Customers | B5: One row per PAYING shop. Renewal_Due within 7 days highlights amber. Overdue + Active highlights red.
A6: Finance | B6: One row per money movement. Balance + Month auto-calc. Revenue cats: Subscription-Monthly/Yearly, Setup fee. Expense cats: Domain, Printing/Poster, Travel/Fuel, Gateway fee.
A7: Dashboard | B7: Formulas only — do not type here. Funnel counts, conversion %, Active MRR, cash MTD, renewals due.
A8: Privacy | B8: Template ships with test-cafe sample only. Do NOT commit real phones / txn refs — keep business data in your local copy.
A9: Regenerate | B9: Edit scripts/generate-tracker.mjs then run: npm run tracker

Sheet Outreach
A1: ID | B1: Date_Added | C1: Shop_Name | D1: Category | E1: Owner_Name | F1: Phone | G1: Area | H1: Stage | I1: Last_Contact | J1: Next_FollowUp | K1: Demo_Done | L1: Objection | M1: Expected_MRR | N1: Lost_Reason | O1: Notes | P1: Days_In_Stage
A2: 1 | B2: 46279.353 | C2: Test Cafe | D2: Cafe | E2: Sample Owner | G2: Sample Area | H2: Demo | I2: 46279.353 | J2: 46281.353 | K2: Y | L2: Price | M2: 299 | O2: Sample — replace with your first real prospect. | P2: =IF(H2="Closed","",IF(I2="","",TODAY()-I2))
P3: =IF(H3="Closed","",IF(I3="","",TODAY()-I3))
P4: =IF(H4="Closed","",IF(I4="","",TODAY()-I4))
P5: =IF(H5="Closed","",IF(I5="","",TODAY()-I5))
P6: =IF(H6="Closed","",IF(I6="","",TODAY()-I6))
P7: =IF(H7="Closed","",IF(I7="","",TODAY()-I7))
P8: =IF(H8="Closed","",IF(I8="","",TODAY()-I8))
P9: =IF(H9="Closed","",IF(I9="","",TODAY()-I9))
P10: =IF(H10="Closed","",IF(I10="","",TODAY()-I10))
P11: =IF(H11="Closed","",IF(I11="","",TODAY()-I11))
P12: =IF(H12="Closed","",IF(I12="","",TODAY()-I12))
P13: =IF(H13="Closed","",IF(I13="","",TODAY()-I13))
P14: =IF(H14="Closed","",IF(I14="","",TODAY()-I14))
... P301: =IF(H301="Closed","",IF(I301="","",TODAY()-I301))

Sheet Merchant_Stats
A1: Week_Start_Mon | B1: Slug | C1: Shop_Name | D1: Count_1_3_Private | E1: Count_4_5 | F1: Total_Feedbacks | G1: Review_Clicks | H1: Review_Conversion_Pct | I1: Poster_On_Wall | J1: ROI_Sent | K1: Notes
A2: 46279.353 | B2: test-cafe | C2: Test Cafe | D2: 2 | E2: 6 | F2: =IF(AND(D2="",E2=""),"",SUM(D2:E2)) | G2: 4 | H2: =IFERROR(IF(E2="","",G2/E2),"") | I2: Y | J2: Y | K2: Sample — copy real numbers from /dashboard each Monday.
F3: =IF(AND(D3="",E3=""),"",SUM(D3:E3)) | H3: =IFERROR(IF(E3="","",G3/E3),"")
F4: =IF(AND(D4="",E4=""),"",SUM(D4:E4)) | H4: =IFERROR(IF(E4="","",G4/E4),"")
F5: =IF(AND(D5="",E5=""),"",SUM(D5:E5)) | H5: =IFERROR(IF(E5="","",G5/E5),"")
F6: =IF(AND(D6="",E6=""),"",SUM(D6:E6)) | H6: =IFERROR(IF(E6="","",G6/E6),"")
F7: =IF(AND(D7="",E7=""),"",SUM(D7:E7)) | H7: =IFERROR(IF(E7="","",G7/E7),"")
F8: =IF(AND(D8="",E8=""),"",SUM(D8:E8)) | H8: =IFERROR(IF(E8="","",G8/E8),"")
F9: =IF(AND(D9="",E9=""),"",SUM(D9:E9)) | H9: =IFERROR(IF(E9="","",G9/E9),"")
F10: =IF(AND(D10="",E10=""),"",SUM(D10:E10)) | H10: =IFERROR(IF(E10="","",G10/E10),"")
F11: =IF(AND(D11="",E11=""),"",SUM(D11:E11)) | H11: =IFERROR(IF(E11="","",G11/E11),"")
F12: =IF(AND(D12="",E12=""),"",SUM(D12:E12)) | H12: =IFERROR(IF(E12="","",G12/E12),"")
F13: =IF(AND(D13="",E13=""),"",SUM(D13:E13)) | H13: =IFERROR(IF(E13="","",G13/E13),"")
F14: =IF(AND(D14="",E14=""),"",SUM(D14:E14)) | H14: =IFERROR(IF(E14="","",G14/E14),"")
... F301: =IF(AND(D301="",E301=""),"",SUM(D301:E301)) | H301: =IFERROR(IF(E301="","",G301/E301),"")

Sheet Product_Feedback
A1: ID | B1: Date | C1: Slug | D1: Shop_Name | E1: Given_By | F1: Channel | G1: Type | H1: Feedback_Verbatim | I1: Priority | J1: Status | K1: Action_Taken | L1: Followed_Up | M1: Days_Open | N1: Notes
A2: 1 | B2: 46279.353 | C2: test-cafe | D2: Test Cafe | E2: Sample Owner | F2: Revisit | G2: Feature request | H2: Sample — QR poster text too small to read from the wall. | I2: P2-important | J2: Open | L2: N | M2: =IF(OR(J2="Done",J2="Won't fix"),"",IF(B2="","",TODAY()-B2)) | N2: Sample — replace with the first real merchant comment.
M3: =IF(OR(J3="Done",J3="Won't fix"),"",IF(B3="","",TODAY()-B3))
M4: =IF(OR(J4="Done",J4="Won't fix"),"",IF(B4="","",TODAY()-B4))
M5: =IF(OR(J5="Done",J5="Won't fix"),"",IF(B5="","",TODAY()-B5))
M6: =IF(OR(J6="Done",J6="Won't fix"),"",IF(B6="","",TODAY()-B6))
M7: =IF(OR(J7="Done",J7="Won't fix"),"",IF(B7="","",TODAY()-B7))
M8: =IF(OR(J8="Done",J8="Won't fix"),"",IF(B8="","",TODAY()-B8))
M9: =IF(OR(J9="Done",J9="Won't fix"),"",IF(B9="","",TODAY()-B9))
M10: =IF(OR(J10="Done",J10="Won't fix"),"",IF(B10="","",TODAY()-B10))
M11: =IF(OR(J11="Done",J11="Won't fix"),"",IF(B11="","",TODAY()-B11))
M12: =IF(OR(J12="Done",J12="Won't fix"),"",IF(B12="","",TODAY()-B12))
M13: =IF(OR(J13="Done",J13="Won't fix"),"",IF(B13="","",TODAY()-B13))
M14: =IF(OR(J14="Done",J14="Won't fix"),"",IF(B14="","",TODAY()-B14))
... M301: =IF(OR(J301="Done",J301="Won't fix"),"",IF(B301="","",TODAY()-B301))

Sheet Customers
A1: Customer_ID | B1: Shop_Name | C1: Slug | D1: Plan | E1: Start_Date | F1: Renewal_Due | G1: Amount_Paid | H1: Pay_Mode | I1: Txn_Ref | J1: Status | K1: Phone | L1: Notes
A2: C-001 | B2: Test Cafe | C2: test-cafe | D2: Monthly ₹299 | E2: 46279.353 | F2: 46309.353 | G2: 299 | H2: UPI | J2: Active | L2: Sample — replace with first paying shop.

Sheet Finance
A1: Date | B1: Type | C1: Category | D1: Detail_Merchant | E1: Amount_In | F1: Amount_Out | G1: Balance | H1: Month
A2: 46279.353 | B2: Revenue | C2: Subscription-Monthly | D2: test-cafe — sample | E2: 299 | G2: =IF(AND(E2="",F2=""),"",SUM(E2)-SUM(F2)) | H2: =IF(A2="","",TEXT(A2,"yyyy-mm"))
A3: 46279.353 | B3: Expense | C3: Printing/Poster | D3: Laminated demo poster (~Rs 20) | F3: 20 | G3: =IF(AND(E3="",F3=""),"",G2+IF(E3="",0,E3)-IF(F3="",0,F3)) | H3: =IF(A3="","",TEXT(A3,"yyyy-mm"))
G4: =IF(AND(E4="",F4=""),"",G3+IF(E4="",0,E4)-IF(F4="",0,F4)) | H4: =IF(A4="","",TEXT(A4,"yyyy-mm"))
G5: =IF(AND(E5="",F5=""),"",G4+IF(E5="",0,E5)-IF(F5="",0,F5)) | H5: =IF(A5="","",TEXT(A5,"yyyy-mm"))
G6: =IF(AND(E6="",F6=""),"",G5+IF(E6="",0,E6)-IF(F6="",0,F6)) | H6: =IF(A6="","",TEXT(A6,"yyyy-mm"))
G7: =IF(AND(E7="",F7=""),"",G6+IF(E7="",0,E7)-IF(F7="",0,F7)) | H7: =IF(A7="","",TEXT(A7,"yyyy-mm"))
G8: =IF(AND(E8="",F8=""),"",G7+IF(E8="",0,E8)-IF(F8="",0,F8)) | H8: =IF(A8="","",TEXT(A8,"yyyy-mm"))
G9: =IF(AND(E9="",F9=""),"",G8+IF(E9="",0,E9)-IF(F9="",0,F9)) | H9: =IF(A9="","",TEXT(A9,"yyyy-mm"))
G10: =IF(AND(E10="",F10=""),"",G9+IF(E10="",0,E10)-IF(F10="",0,F10)) | H10: =IF(A10="","",TEXT(A10,"yyyy-mm"))
G11: =IF(AND(E11="",F11=""),"",G10+IF(E11="",0,E11)-IF(F11="",0,F11)) | H11: =IF(A11="","",TEXT(A11,"yyyy-mm"))
G12: =IF(AND(E12="",F12=""),"",G11+IF(E12="",0,E12)-IF(F12="",0,F12)) | H12: =IF(A12="","",TEXT(A12,"yyyy-mm"))
G13: =IF(AND(E13="",F13=""),"",G12+IF(E13="",0,E13)-IF(F13="",0,F13)) | H13: =IF(A13="","",TEXT(A13,"yyyy-mm"))
G14: =IF(AND(E14="",F14=""),"",G13+IF(E14="",0,E14)-IF(F14="",0,F14)) | H14: =IF(A14="","",TEXT(A14,"yyyy-mm"))
G15: =IF(AND(E15="",F15=""),"",G14+IF(E15="",0,E15)-IF(F15="",0,F15)) | H15: =IF(A15="","",TEXT(A15,"yyyy-mm"))
... G301: =IF(AND(E301="",F301=""),"",G300+IF(E301="",0,E301)-IF(F301="",0,F301)) | H301: =IF(A301="","",TEXT(A301,"yyyy-mm"))

Sheet Dashboard
A1: Metric | B1: Value | C1: Formula / note
A2: Funnel — Prospect | B2: =COUNTIF(Outreach!H2:H301,"Prospect") | C2: Count of Outreach Stage
A3: Funnel — Lead | B3: =COUNTIF(Outreach!H2:H301,"Lead")
A4: Funnel — Walk-in | B4: =COUNTIF(Outreach!H2:H301,"Walk-in")
A5: Funnel — Demo | B5: =COUNTIF(Outreach!H2:H301,"Demo")
A6: Funnel — Negotiation | B6: =COUNTIF(Outreach!H2:H301,"Negotiation")
A7: Funnel — Closed | B7: =COUNTIF(Outreach!H2:H301,"Closed")
A8: Funnel — Lost | B8: =COUNTIF(Outreach!H2:H301,"Lost")
A9: Close rate (Closed / decided) | B9: =IFERROR(COUNTIF(Outreach!H2:H301,"Closed")/MAX(1,COUNTIF(Outreach!H2:H301,"Closed")+COUNTIF(Outreach!H2:H301,"Lost")),"") | C9: Format as % in Excel
A10: Active Monthly subs | B10: =COUNTIFS(Customers!D2:D301,"Monthly ₹299",Customers!J2:J301,"Active") | C10: Plan strings must match dropdown
A11: Active Yearly subs | B11: =COUNTIFS(Customers!D2:D301,"Yearly ₹2999",Customers!J2:J301,"Active")
A12: Active MRR (Rs) | B12: =B10*299+B11*2999/12 | C12: Yearly amortised /12
A13: Cash IN this month (Rs) | B13: =SUMIFS(Finance!E2:E301,Finance!H2:H301,TEXT(TODAY(),"yyyy-mm")) | C13: Uses Finance Month col
A14: Cash OUT this month (Rs) | B14: =SUMIFS(Finance!F2:F301,Finance!H2:H301,TEXT(TODAY(),"yyyy-mm"))
A15: Net this month (Rs) | B15: =B13-B14
A16: Renewals due next 7d | B16: =COUNTIFS(Customers!F2:F301,">="&TODAY(),Customers!F2:F301,"<="&TODAY()+7,Customers!J2:J301,"Active") | C16: Chase on WhatsApp (SALES.md Day-30 loop)
A17: Renewals OVERDUE | B17: =COUNTIFS(Customers!F2:F301,"<"&TODAY(),Customers!J2:J301,"Active") | C17: Visit beats 3 messages
A18: Feedbacks last 28d | B18: =SUMIFS(Merchant_Stats!F2:F301,Merchant_Stats!A2:A301,">="&TODAY()-28)
A19: Review clicks last 28d | B19: =SUMIFS(Merchant_Stats!G2:G301,Merchant_Stats!A2:A301,">="&TODAY()-28) | C19: ROI line for renewal WhatsApp
A20: Product feedback — Open | B20: =COUNTIF(Product_Feedback!J2:J301,"Open") | C20: Triage weekly; follow up before renewals
A21: Product feedback — P1 open | B21: =COUNTIFS(Product_Feedback!I2:I301,"P1-critical",Product_Feedback!J2:J301,"Open")+COUNTIFS(Product_Feedback!I2:I301,"P1-critical",Product_Feedback!J2:J301,"In Progress") | C21: Fix first
A22: Churn risks open | B22: =COUNTIFS(Product_Feedback!G2:G301,"Churn risk",Product_Feedback!J2:J301,"Open")+COUNTIFS(Product_Feedback!G2:G301,"Churn risk",Product_Feedback!J2:J301,"In Progress") | C22: Visit beats 3 messages
A23: Product feedback — Done 28d | B23: =COUNTIFS(Product_Feedback!J2:J301,"Done",Product_Feedback!B2:B301,">="&TODAY()-28) | C23: Velocity; reuse as renewal-WA proof
